{
  "id": "KB-662",
  "description": "When dashboard becomes visible refresh data",
  "column": "in-progress",
  "size": "S",
  "reviewLevel": 1,
  "currentStep": 0,
  "worktree": "/Users/eclipxe/Projects/kb/.worktrees/quiet-plume",
  "baseCommitSha": "e478311c531d314b7f2ce3d95fd08aad67b05b7c",
  "createdAt": "2026-04-01T05:35:18.262Z",
  "updatedAt": "2026-04-01T14:00:36.543Z",
  "columnMovedAt": "2026-04-01T14:00:20.319Z",
  "dependencies": [],
  "steps": [
    {
      "name": "Add Visibility Change Listener",
      "status": "in-progress"
    },
    {
      "name": "Testing & Verification",
      "status": "pending"
    },
    {
      "name": "Documentation & Delivery",
      "status": "pending"
    }
  ],
  "log": [
    {
      "timestamp": "2026-04-01T05:35:18.262Z",
      "action": "Task created"
    },
    {
      "timestamp": "2026-04-01T05:40:58.638Z",
      "action": "Spec review requested"
    },
    {
      "timestamp": "2026-04-01T05:41:11.521Z",
      "action": "Spec review: APPROVE",
      "outcome": "The specification is well-crafted for a small, focused change. It correctly identifies the target files, describes concrete implementation steps with verifiable outcomes, and specifies appropriate testing requirements. The mission is clear, the file scope is accurate, and the sizing (S, Review Level 1) is appropriate for this low-blast-radius feature."
    },
    {
      "timestamp": "2026-04-01T14:00:20.556Z",
      "action": "Worktree created at /Users/eclipxe/Projects/kb/.worktrees/quiet-plume"
    },
    {
      "timestamp": "2026-04-01T14:00:20.577Z",
      "action": "Step 0 (Add Visibility Change Listener) → pending"
    },
    {
      "timestamp": "2026-04-01T14:00:36.543Z",
      "action": "Step 0 (Add Visibility Change Listener) → in-progress"
    }
  ]
}